README.rst
setup.py
src/Pydblibrary/__init__.py
src/Pydblibrary/connection_manager.py
src/Pydblibrary/version.py
src/Pydblibrary/keywords/__init__.py
src/Pydblibrary/keywords/_common.py
src/Pydblibrary/keywords/_execution.py
src/Pydblibrary/keywords/_existence.py
src/Pydblibrary/keywords/_rows.py
src/Pydblibrary/keywords/_table.py
src/robotframework_pydblibrary.egg-info/PKG-INFO
src/robotframework_pydblibrary.egg-info/SOURCES.txt
src/robotframework_pydblibrary.egg-info/dependency_links.txt
src/robotframework_pydblibrary.egg-info/not-zip-safe
src/robotframework_pydblibrary.egg-info/requires.txt
src/robotframework_pydblibrary.egg-info/top_level.txt