Metadata-Version: 1.0
Name: robotframework-pydblibrary
Version: 1.1
Summary: Python Database utility library for Robot Framework
Home-page: https://github.com/F1ashhimself/robotframework-pydblibrary
Author: Max Beloborodko
Author-email: f1ashhimself@gmail.com
License: Apache License 2.0
Platform: any
